rin/curium/__init__.py
rin/curium/_logger.py
rin/curium/command_base.py
rin/curium/connections.py
rin/curium/constants.py
rin/curium/exc.py
rin/curium/iconnection.py
rin/curium/iserializer.py
rin/curium/node.py
rin/curium/response_handler_base.py
rin/curium/response_handlers.py
rin/curium/serializers.py
rin/curium/utils.py
rin/curium/commands/__init__.py
rin/curium/commands/add_response.py
rin/curium/commands/command_wrapper.py
rin/curium/commands/get_node_infos.py
rin_curium-0.2.0.dist-info/LICENSE
rin_curium-0.2.0.dist-info/METADATA
rin_curium-0.2.0.dist-info/WHEEL
rin_curium-0.2.0.dist-info/top_level.txt
rin_curium-0.2.0.dist-info/RECORD
