Metadata-Version: 2.1
Name: rin-curium
Version: 0.2.0
Summary: rin-curium is a packages intended to resolve internodes communication
License: MIT License
Project-URL: GitHub, https://github.com/susautw/rin-curium
Keywords: communication,command
Classifier: Programming Language :: Python :: 3
Classifier: License :: OSI Approved :: MIT License
Classifier: Operating System :: OS Independent
Requires-Python: >=3.8
License-File: LICENSE
Requires-Dist: fancy-config (~=0.12.0)
Requires-Dist: rin-jsonutils (~=1.1.0)
Requires-Dist: rin-docutils (~=1.0.0)
Requires-Dist: redis (~=4.3.4)
